midox/DataTypeConverters.py
midox/EventDispatcher.py
midox/MidiFileParser.py
midox/MidiInFile.py
midox/MidiInStream.py
midox/MidiOutFile.py
midox/MidiOutStream.py
midox/MidiToText.py
midox/RawInstreamFile.py
midox/RawOutstreamFile.py
midox/__init__.py
midox/constants.py
midox/example_mimimal_type0.py
midox/example_print_channel_0.py
midox/example_print_events.py
midox/example_print_file.py
midox/example_transpose_octave.py
midox/midi_utils.py
midox-0.1.0.dist-info/METADATA
midox-0.1.0.dist-info/WHEEL
midox-0.1.0.dist-info/licenses/license.txt
midox-0.1.0.dist-info/RECORD
