Metadata-Version: 2.1
Name: midox
Version: 0.1.0
Summary: A package to help read music. Credits given to everyone who contributed to building this.
Project-URL: Homepage, https://github.com/jmcarpenter2/music-generation/tree/master/midi
Author-email: just_some_person <allyouneedgenuine@gmail.com>
License-File: license.txt
Classifier: License :: OSI Approved :: MIT License
Classifier: Operating System :: OS Independent
Classifier: Programming Language :: Python :: 3
Requires-Python: >=3.7
